HitAlibabaBishiMianshiZhishiZhengli/README.md
HitAlibabaBishiMianshiZhishiZhengli/__init__.py
HitAlibabaBishiMianshiZhishiZhengli/__main__.py
HitAlibabaBishiMianshiZhishiZhengli/file.epub
HitAlibabaBishiMianshiZhishiZhengli/index.html
HitAlibabaBishiMianshiZhishiZhengli/css/__init__.py
HitAlibabaBishiMianshiZhishiZhengli/css/annotations.css
HitAlibabaBishiMianshiZhishiZhengli/css/main.css
HitAlibabaBishiMianshiZhishiZhengli/css/normalize.css
HitAlibabaBishiMianshiZhishiZhengli/css/popup.css
HitAlibabaBishiMianshiZhishiZhengli/font/__init__.py
HitAlibabaBishiMianshiZhishiZhengli/font/fontello.eot
HitAlibabaBishiMianshiZhishiZhengli/font/fontello.svg
HitAlibabaBishiMianshiZhishiZhengli/font/fontello.ttf
HitAlibabaBishiMianshiZhishiZhengli/font/fontello.woff
HitAlibabaBishiMianshiZhishiZhengli/img/__init__.py
HitAlibabaBishiMianshiZhishiZhengli/img/annotator-glyph-sprite.png
HitAlibabaBishiMianshiZhishiZhengli/img/annotator-icon-sprite.png
HitAlibabaBishiMianshiZhishiZhengli/img/apple-touch-icon.png
HitAlibabaBishiMianshiZhishiZhengli/img/cancelfullscreen.png
HitAlibabaBishiMianshiZhishiZhengli/img/close.png
HitAlibabaBishiMianshiZhishiZhengli/img/fullscreen.png
HitAlibabaBishiMianshiZhishiZhengli/img/loader.gif
HitAlibabaBishiMianshiZhishiZhengli/img/menu-icon.png
HitAlibabaBishiMianshiZhishiZhengli/img/save.png
HitAlibabaBishiMianshiZhishiZhengli/img/saved.png
HitAlibabaBishiMianshiZhishiZhengli/img/settings-s.png
HitAlibabaBishiMianshiZhishiZhengli/img/settings.png
HitAlibabaBishiMianshiZhishiZhengli/img/star.png
HitAlibabaBishiMianshiZhishiZhengli/js/__init__.py
HitAlibabaBishiMianshiZhishiZhengli/js/epub.js
HitAlibabaBishiMianshiZhishiZhengli/js/epub.min.js
HitAlibabaBishiMianshiZhishiZhengli/js/epub.min.map
HitAlibabaBishiMianshiZhishiZhengli/js/hooks.min.js
HitAlibabaBishiMianshiZhishiZhengli/js/hooks.min.map
HitAlibabaBishiMianshiZhishiZhengli/js/reader.js
HitAlibabaBishiMianshiZhishiZhengli/js/reader.js.map
HitAlibabaBishiMianshiZhishiZhengli/js/reader.min.js
hit_alibaba_bishi_mianshi_zhishi_zhengli-2024.3.4.0.dist-info/METADATA
hit_alibaba_bishi_mianshi_zhishi_zhengli-2024.3.4.0.dist-info/WHEEL
hit_alibaba_bishi_mianshi_zhishi_zhengli-2024.3.4.0.dist-info/entry_points.txt
hit_alibaba_bishi_mianshi_zhishi_zhengli-2024.3.4.0.dist-info/top_level.txt
hit_alibaba_bishi_mianshi_zhishi_zhengli-2024.3.4.0.dist-info/RECORD
